clod/__init__.py
clod/cli.py
clod/config_models.py
clod/desktop_mcp.py
clod/hooks.py
clod/log_parser.py
clod/sfx.py
clod/streaming.py
clod/tmux.py
clod/models/__init__.py
clod/models/claude_log.py
clodd-1.0.0.dist-info/METADATA
clodd-1.0.0.dist-info/WHEEL
clodd-1.0.0.dist-info/entry_points.txt
clodd-1.0.0.dist-info/licenses/LICENSE
clodd-1.0.0.dist-info/RECORD
