Metadata-Version: 2.4
Name: clodd
Version: 1.0.0
Summary: Claude utilities and hacks
Author-email: ghostbloo <ghostbloo@users.noreply.github.com>
License: MIT
License-File: LICENSE
Keywords: ai,claude,cli,productivity,tmux
Classifier: Development Status :: 4 - Beta
Classifier: Intended Audience :: Developers
Classifier: License :: OSI Approved :: MIT License
Classifier: Programming Language :: Python :: 3
Classifier: Programming Language :: Python :: 3.13
Classifier: Topic :: Software Development :: Libraries :: Python Modules
Classifier: Topic :: Utilities
Requires-Python: >=3.13
Requires-Dist: cchooks>=0.1.0
Requires-Dist: claude-code-sdk>=0.0.17
Requires-Dist: click>=8.0.0
Requires-Dist: pydantic>=2.11.7
Requires-Dist: textual>=0.82.0
Requires-Dist: watchdog>=5.0.0
Requires-Dist: websockets>=13.0.0
